Metadata-Version: 2.1
Name: py-version-tracker
Version: 0.0.1
Summary: PyVersionTracker is a Python utility for tracking and managing Python versions.
Home-page: https://github.com/yousefabuz17/PyVersionTracker
Download-URL: https://github.com/yousefabuz17/PyVersionTracker.git
Author: Yousef Abuzahrieh
Author-email: yousefzahrieh17@gmail.com
License: Apache Software License
Platform: Windows
Platform: Linux
Platform: MacOS
Classifier: Programming Language :: Python :: 3
Classifier: License :: OSI Approved :: Apache Software License
Classifier: Operating System :: OS Independent
License-File: LICENSE.md
Requires-Dist: aiohttp~=3.9.0b0
Requires-Dist: beautifulsoup4~=4.12.2
Requires-Dist: setuptools~=68.2.2
Requires-Dist: pypistats~=1.5.0
